{"_type":"export","__export_format":4,"__export_date":"2022-09-25T06:59:42.151Z","__export_source":"insomnia.desktop.app:v2022.4.2","resources":[{"_id":"req_d7f20ee55385402b8fe89fac5ae50b0f","parentId":"fld_eda5eb2e79424d70b9486274465556f8","modified":1656912920979,"created":1656912874636,"url":"http://localhost:3001/page1","name":"page1","description":"","method":"GET","body":{},"parameters":[],"headers":[],"authentication":{},"metaSortKey":-1651286128704,"isPrivate":false,"settingStoreCookies":true,"settingSendCookies":true,"settingDisableRenderRequestBody":false,"settingEncodeUrl":true,"settingRebuildPath":true,"settingFollowRedirects":"global","_type":"request"},{"_id":"fld_eda5eb2e79424d70b9486274465556f8","parentId":"wrk_e0c56d5920114de58ae9b756107d37a9","modified":1656912974759,"created":1656912914072,"name":"Setup","description":"","environment":{},"environmentPropertyOrder":null,"metaSortKey":-1656912971963,"_type":"request_group"},{"_id":"wrk_e0c56d5920114de58ae9b756107d37a9","parentId":null,"modified":1656915802180,"created":1651285914877,"name":"Node.js Express 단위 테스트","description":"이젠 아카데미 Node.js 수업의 단위 테스트 요청 정의 입니다.","scope":"collection","_type":"workspace"},{"_id":"req_480ffa84085841a48b975a016145d870","parentId":"fld_eda5eb2e79424d70b9486274465556f8","modified":1656912938270,"created":1656912924088,"url":"http://localhost:3001/page2","name":"page2","description":"","method":"GET","body":{},"parameters":[],"headers":[],"authentication":{},"metaSortKey":-1651286128654,"isPrivate":false,"settingStoreCookies":true,"settingSendCookies":true,"settingDisableRenderRequestBody":false,"settingEncodeUrl":true,"settingRebuildPath":true,"settingFollowRedirects":"global","_type":"request"},{"_id":"req_9bf1106eb7aa43748eb58e2e81f19661","parentId":"fld_eda5eb2e79424d70b9486274465556f8","modified":1656912951295,"created":1656912944022,"url":"http://localhost:3001/page3","name":"page3","description":"","method":"GET","body":{},"parameters":[],"headers":[],"authentication":{},"metaSortKey":-1651286128604,"isPrivate":false,"settingStoreCookies":true,"settingSendCookies":true,"settingDisableRenderRequestBody":false,"settingEncodeUrl":true,"settingRebuildPath":true,"settingFollowRedirects":"global","_type":"request"},{"_id":"req_b66668ebe7cd4a1e9aa7c2ae92bf7638","parentId":"fld_cd75d58790554a4e889bc799b48cf5ef","modified":1656984616487,"created":1651286128754,"url":"http://localhost:3001/send_get","name":"send_get","description":"","method":"GET","body":{},"parameters":[{"id":"pair_e7bb119d9af243408433f393ad39238f","name":"answer","value":"300","description":""},{"id":"pair_1791f3cfb096460a9211276655753f6d","name":"name","value":"student","description":"","disabled":false},{"id":"pair_b2788e3a86dc4be4b35c4d6b368cce4f","name":"age","value":"20","description":""}],"headers":[],"authentication":{},"metaSortKey":-1651286128754,"isPrivate":false,"settingStoreCookies":true,"settingSendCookies":true,"settingDisableRenderRequestBody":false,"settingEncodeUrl":true,"settingRebuildPath":true,"settingFollowRedirects":"global","_type":"request"},{"_id":"fld_cd75d58790554a4e889bc799b48cf5ef","parentId":"wrk_e0c56d5920114de58ae9b756107d37a9","modified":1656912971913,"created":1656912971913,"name":"GetParams","description":"","environment":{},"environmentPropertyOrder":null,"metaSortKey":-1656912971913,"_type":"request_group"},{"_id":"req_f489482e0f2c4300b6e77ef460f61fcf","parentId":"fld_cd75d58790554a4e889bc799b48cf5ef","modified":1656912986783,"created":1651286309199,"url":"http://localhost:3001/send_url/helloworld/19","name":"send_url","description":"","method":"GET","body":{},"parameters":[],"headers":[],"authentication":{},"metaSortKey":-1651286128704,"isPrivate":false,"settingStoreCookies":true,"settingSendCookies":true,"settingDisableRenderRequestBody":false,"settingEncodeUrl":true,"settingRebuildPath":true,"settingFollowRedirects":"global","_type":"request"},{"_id":"req_5e78d5893f0b4ff4a8c3935690d300df","parentId":"fld_6c2e4475b4614d35a3d5383a41c43245","modified":1656913014028,"created":1651286345772,"url":"http://localhost:3001/send_post","name":"send_post","description":"","method":"POST","body":{"mimeType":"application/x-www-form-urlencoded","params":[{"id":"pair_95c74688cf634095b7622d790424ec30","name":"username","value":"헬로월드","description":""},{"id":"pair_c82daedb16e7492f979066c19b013407","name":"email","value":"helloworld@naver.com","description":""}]},"parameters":[],"headers":[{"name":"Content-Type","value":"application/x-www-form-urlencoded","id":"pair_c1d0b0f6034346db9bc9d6e7294e6354"}],"authentication":{},"metaSortKey":-1651286345772,"isPrivate":false,"settingStoreCookies":true,"settingSendCookies":true,"settingDisableRenderRequestBody":false,"settingEncodeUrl":true,"settingRebuildPath":true,"settingFollowRedirects":"global","_type":"request"},{"_id":"fld_6c2e4475b4614d35a3d5383a41c43245","parentId":"wrk_e0c56d5920114de58ae9b756107d37a9","modified":1656913008731,"created":1656913005483,"name":"Post,Put,Delete","description":"","environment":{},"environmentPropertyOrder":null,"metaSortKey":-1654110172618,"_type":"request_group"},{"_id":"req_0d2a44a443044df1b6a0c75967c106b1","parentId":"fld_6c2e4475b4614d35a3d5383a41c43245","modified":1656913016364,"created":1651286510299,"url":"http://localhost:3001/send_put","name":"send_put","description":"","method":"PUT","body":{"mimeType":"application/x-www-form-urlencoded","params":[{"id":"pair_cb4c932dd6514d4dae91c5ca2ef224df","name":"username","value":"노드학생","description":""},{"id":"pair_a4b99e58dae74bdea47e6bc3ca4e26c5","name":"grade","value":"4","description":""}]},"parameters":[],"headers":[{"name":"Content-Type","value":"application/x-www-form-urlencoded","id":"pair_d612eb84cb934d488942f6f8eeee60ce"}],"authentication":{},"metaSortKey":-1651286345722,"isPrivate":false,"settingStoreCookies":true,"settingSendCookies":true,"settingDisableRenderRequestBody":false,"settingEncodeUrl":true,"settingRebuildPath":true,"settingFollowRedirects":"global","_type":"request"},{"_id":"req_b74b0be621b9406bbf6da612ba13e1d1","parentId":"fld_6c2e4475b4614d35a3d5383a41c43245","modified":1656913018375,"created":1651286574846,"url":"http://localhost:3001/send_delete","name":"send_delete","description":"","method":"DELETE","body":{"mimeType":"application/x-www-form-urlencoded","params":[{"id":"pair_32b678227b334104bec66b1abf0bb4bd","name":"username","value":"이광호","description":""},{"id":"pair_96b73d429c8e4b39b87469cb0734af75","name":"point","value":"64","description":""}]},"parameters":[],"headers":[{"name":"Content-Type","value":"application/x-www-form-urlencoded","id":"pair_608045e99d704ed9a19d10851f92af3a"}],"authentication":{},"metaSortKey":-1651286345672,"isPrivate":false,"settingStoreCookies":true,"settingSendCookies":true,"settingDisableRenderRequestBody":false,"settingEncodeUrl":true,"settingRebuildPath":true,"settingFollowRedirects":"global","_type":"request"},{"_id":"req_1aec40d6b785482fa065ed7935e2b462","parentId":"fld_6c2e4475b4614d35a3d5383a41c43245","modified":1656913024828,"created":1651286775595,"url":"http://localhost:3001/product/5555","name":"product get","description":"","method":"GET","body":{},"parameters":[],"headers":[],"authentication":{},"metaSortKey":-1651286345622,"isPrivate":false,"settingStoreCookies":true,"settingSendCookies":true,"settingDisableRenderRequestBody":false,"settingEncodeUrl":true,"settingRebuildPath":true,"settingFollowRedirects":"global","_type":"request"},{"_id":"req_4803b6e8e50c42fc927bc6fefe1c3f60","parentId":"fld_6c2e4475b4614d35a3d5383a41c43245","modified":1656913027403,"created":1651286866778,"url":"http://localhost:3001/product","name":"product post","description":"","method":"POST","body":{"mimeType":"application/x-www-form-urlencoded","params":[{"id":"pair_992d661d783f498999a036d8e4c20895","name":"productNumber","value":"5555","description":""},{"id":"pair_39ee239620e14f6daa05b87c9497b418","name":"productName","value":"티셔츠","description":""},{"id":"pair_a3bfc7b1eb9746a394e90dc1093123fd","name":"qty","value":"5","description":""}]},"parameters":[],"headers":[{"name":"Content-Type","value":"application/x-www-form-urlencoded","id":"pair_5be4de51153d40a7a4e88fced27dc0c7"}],"authentication":{},"metaSortKey":-1651286345572,"isPrivate":false,"settingStoreCookies":true,"settingSendCookies":true,"settingDisableRenderRequestBody":false,"settingEncodeUrl":true,"settingRebuildPath":true,"settingFollowRedirects":"global","_type":"request"},{"_id":"req_4db9d61716414483a95733e9d02f21cd","parentId":"fld_6c2e4475b4614d35a3d5383a41c43245","modified":1656913029221,"created":1651286882379,"url":"http://localhost:3001/product/5555","name":"product put","description":"","method":"PUT","body":{"mimeType":"application/x-www-form-urlencoded","params":[{"id":"pair_39ee239620e14f6daa05b87c9497b418","name":"productName","value":"티셔츠","description":""},{"id":"pair_a3bfc7b1eb9746a394e90dc1093123fd","name":"qty","value":"5","description":""}]},"parameters":[],"headers":[{"name":"Content-Type","value":"application/x-www-form-urlencoded","id":"pair_5be4de51153d40a7a4e88fced27dc0c7"}],"authentication":{},"metaSortKey":-1651286345522,"isPrivate":false,"settingStoreCookies":true,"settingSendCookies":true,"settingDisableRenderRequestBody":false,"settingEncodeUrl":true,"settingRebuildPath":true,"settingFollowRedirects":"global","_type":"request"},{"_id":"req_190d2c9f99b8471fb757468e6e7814ec","parentId":"fld_6c2e4475b4614d35a3d5383a41c43245","modified":1656913030997,"created":1651286899189,"url":"http://localhost:3001/product/1234","name":"product delete","description":"","method":"DELETE","body":{"mimeType":"application/x-www-form-urlencoded","params":[]},"parameters":[],"headers":[{"name":"Content-Type","value":"application/x-www-form-urlencoded","id":"pair_5be4de51153d40a7a4e88fced27dc0c7"}],"authentication":{},"metaSortKey":-1651286345472,"isPrivate":false,"settingStoreCookies":true,"settingSendCookies":true,"settingDisableRenderRequestBody":false,"settingEncodeUrl":true,"settingRebuildPath":true,"settingFollowRedirects":"global","_type":"request"},{"_id":"req_a56d10b7a5794db685cf14a447e9bd2e","parentId":"fld_8718ba74a06d4250a328b5dc59eea339","modified":1656913120043,"created":1656913071236,"url":"http://localhost:3001/cookie","name":"cookie","description":"","method":"POST","body":{"mimeType":"application/x-www-form-urlencoded","params":[{"id":"pair_3a4858e0e29c4511862370236be843d0","name":"my_msg","value":"안녕하세요. 쿠키 테스트","description":""},{"id":"pair_a60c980dab624108afd60243d32b9361","name":"my_msg_signed","value":"안녕하세요. 암호화 쿠키 테스트","description":""}]},"parameters":[],"headers":[{"name":"Content-Type","value":"application/x-www-form-urlencoded","id":"pair_849448c964ad48bbbcc10822cfa7ff95"}],"authentication":{},"metaSortKey":-1656913071236,"isPrivate":false,"settingStoreCookies":true,"settingSendCookies":true,"settingDisableRenderRequestBody":false,"settingEncodeUrl":true,"settingRebuildPath":true,"settingFollowRedirects":"global","_type":"request"},{"_id":"fld_8718ba74a06d4250a328b5dc59eea339","parentId":"wrk_e0c56d5920114de58ae9b756107d37a9","modified":1656913063596,"created":1656913060660,"name":"Cookie","description":"","environment":{},"environmentPropertyOrder":null,"metaSortKey":-1652708772970.5,"_type":"request_group"},{"_id":"req_c1be99e3e66547d1b7870af7e8832c29","parentId":"fld_8718ba74a06d4250a328b5dc59eea339","modified":1656913133319,"created":1656913122787,"url":"http://localhost:3001/cookie","name":"cookie","description":"","method":"GET","body":{},"parameters":[],"headers":[],"authentication":{},"metaSortKey":-1656913071186,"isPrivate":false,"settingStoreCookies":true,"settingSendCookies":true,"settingDisableRenderRequestBody":false,"settingEncodeUrl":true,"settingRebuildPath":true,"settingFollowRedirects":"global","_type":"request"},{"_id":"req_85f580f72d7742d4afb004bd3c2a8990","parentId":"fld_8718ba74a06d4250a328b5dc59eea339","modified":1656913172829,"created":1656913163094,"url":"http://localhost:3001/cookie","name":"cookie","description":"","method":"DELETE","body":{},"parameters":[],"headers":[],"authentication":{},"metaSortKey":-1656913071136,"isPrivate":false,"settingStoreCookies":true,"settingSendCookies":true,"settingDisableRenderRequestBody":false,"settingEncodeUrl":true,"settingRebuildPath":true,"settingFollowRedirects":"global","_type":"request"},{"_id":"req_b8531436ddfa499c9d321dd54733e17f","parentId":"fld_c1276b1d58594cfdaa2d82198953e412","modified":1656913192841,"created":1651298455519,"url":"http://localhost:3001/session","name":"session","description":"","method":"POST","body":{"mimeType":"application/x-www-form-urlencoded","params":[{"id":"pair_e5c30790a14a4dd3a5c5e9d3af45b5de","name":"username","value":"세션테스트","description":""},{"id":"pair_b6fcb892f6b64cbf91d3ec904dabb711","name":"nickname","value":"session test","description":""}]},"parameters":[],"headers":[{"name":"Content-Type","value":"application/x-www-form-urlencoded","id":"pair_f9e6d8a5ef85495e9d62023e0cc3975c"}],"authentication":{},"metaSortKey":-1651299226546,"isPrivate":false,"settingStoreCookies":true,"settingSendCookies":true,"settingDisableRenderRequestBody":false,"settingEncodeUrl":true,"settingRebuildPath":true,"settingFollowRedirects":"global","_type":"request"},{"_id":"fld_c1276b1d58594cfdaa2d82198953e412","parentId":"wrk_e0c56d5920114de58ae9b756107d37a9","modified":1656913490594,"created":1656913185261,"name":"Session","description":"","environment":{},"environmentPropertyOrder":null,"metaSortKey":-1652533598014.5625,"_type":"request_group"},{"_id":"req_33c892d314e74849b3c0e0cb4c4a93bb","parentId":"fld_c1276b1d58594cfdaa2d82198953e412","modified":1656913190900,"created":1651299226496,"url":"http://localhost:3001/session","name":"session","description":"","method":"GET","body":{},"parameters":[],"headers":[],"authentication":{},"metaSortKey":-1651299226496,"isPrivate":false,"settingStoreCookies":true,"settingSendCookies":true,"settingDisableRenderRequestBody":false,"settingEncodeUrl":true,"settingRebuildPath":true,"settingFollowRedirects":"global","_type":"request"},{"_id":"req_859730f956f04386a590923cf812a7be","parentId":"fld_c1276b1d58594cfdaa2d82198953e412","modified":1657069514961,"created":1656913199813,"url":"http://localhost:3001/session/login","name":"login","description":"","method":"POST","body":{"mimeType":"application/x-www-form-urlencoded","params":[{"id":"pair_ce5eccfd446240faa94b730775606299","name":"userid","value":"node","description":""},{"id":"pair_38a43b42d94641c98489d8fc523c94c3","name":"userpw","value":"1234","description":""}]},"parameters":[],"headers":[{"name":"Content-Type","value":"application/x-www-form-urlencoded","id":"pair_774e8060093941d9a93baeea6d8aa20f"}],"authentication":{},"metaSortKey":-1651299226446,"isPrivate":false,"settingStoreCookies":true,"settingSendCookies":true,"settingDisableRenderRequestBody":false,"settingEncodeUrl":true,"settingRebuildPath":true,"settingFollowRedirects":"global","_type":"request"},{"_id":"req_853b60f55f91447e9e1bb6590352cbb4","parentId":"fld_c1276b1d58594cfdaa2d82198953e412","modified":1656913401867,"created":1656913387539,"url":"http://localhost:3001/session/login","name":"login","description":"","method":"GET","body":{},"parameters":[],"headers":[],"authentication":{},"metaSortKey":-1651299226396,"isPrivate":false,"settingStoreCookies":true,"settingSendCookies":true,"settingDisableRenderRequestBody":false,"settingEncodeUrl":true,"settingRebuildPath":true,"settingFollowRedirects":"global","_type":"request"},{"_id":"req_12bfcd0eea934f34bf7592f76a0215f3","parentId":"fld_c1276b1d58594cfdaa2d82198953e412","modified":1656913468000,"created":1656913452168,"url":"http://localhost:3001/session/login","name":"login","description":"","method":"DELETE","body":{},"parameters":[],"headers":[],"authentication":{},"metaSortKey":-1651299226346,"isPrivate":false,"settingStoreCookies":true,"settingSendCookies":true,"settingDisableRenderRequestBody":false,"settingEncodeUrl":true,"settingRebuildPath":true,"settingFollowRedirects":"global","_type":"request"},{"_id":"req_9b4bfc8270bd4b1aaf0124a03b6f6602","parentId":"fld_700a5937dcc24004bb8c8922edab600a","modified":1657072322949,"created":1656942147481,"url":"http://localhost:3001/send_mail","name":"send_mail","description":"","method":"POST","body":{"mimeType":"application/x-www-form-urlencoded","params":[{"id":"pair_6082cf4385b24294b133f2d3d069ca0c","name":"writer_name","value":"백엔드 개발자","description":"","disabled":false},{"id":"pair_e8f93cc8fbfd4ffe8e39f945600e17d0","name":"writer_email","value":"leekh4232@gmail.com","description":"","disabled":false},{"id":"pair_7eeb0146220e464dabc67e5e1eb2ba20","name":"receiver_name","value":"프론트 개발자","description":"","disabled":false},{"id":"pair_2f038d5a9ffe45558068aa49751ed6fd","name":"receiver_email","value":"totory3217@naver.com","description":"","disabled":false},{"id":"pair_967b2f164e32489db86a648f9e53fef6","name":"subject","value":"노드JS 메일 발송 테스트","description":"","disabled":false},{"id":"pair_6517e3a14d5c4654a7bb3064deb1f422","name":"content","value":"<h1>Hello World</h1><p>반갑습니다. Node.js 메일 발송 테스트 입니다.</p>","description":"","type":"text","multiline":false,"disabled":false}]},"parameters":[],"headers":[{"name":"Content-Type","value":"application/x-www-form-urlencoded","id":"pair_5b00896917d34f4fade65d80b592846a"}],"authentication":{},"metaSortKey":-1656942147481,"isPrivate":false,"settingStoreCookies":true,"settingSendCookies":true,"settingDisableRenderRequestBody":false,"settingEncodeUrl":true,"settingRebuildPath":true,"settingFollowRedirects":"global","_type":"request"},{"_id":"fld_700a5937dcc24004bb8c8922edab600a","parentId":"wrk_e0c56d5920114de58ae9b756107d37a9","modified":1656915899927,"created":1656915896495,"name":"SendMail","description":"","environment":{},"environmentPropertyOrder":null,"metaSortKey":-1652446010536.5938,"_type":"request_group"},{"_id":"req_77537e547d484e98878adf54fe9734c6","parentId":"fld_94f8df7cbf76416ca4253b827ae84d5c","modified":1656913480737,"created":1651307026635,"url":"http://localhost:3001/upload/single","name":"single upload","description":"","method":"POST","body":{"mimeType":"multipart/form-data","params":[{"id":"pair_1ac95ff2a3c04d6c8ad7cbc37a86cc66","name":"myphoto","value":"","description":"","type":"file","fileName":"/Users/leekh/Dropbox (아이티페이퍼)/카메라 백업/배경화면/여름/01661_privatedocksunset_2560x1600.jpg"}]},"parameters":[],"headers":[{"name":"Content-Type","value":"multipart/form-data","id":"pair_d1741e47e8494baf9ae43c32059dca8f"}],"authentication":{},"metaSortKey":-1651307373373,"isPrivate":false,"settingStoreCookies":true,"settingSendCookies":true,"settingDisableRenderRequestBody":false,"settingEncodeUrl":true,"settingRebuildPath":true,"settingFollowRedirects":"global","_type":"request"},{"_id":"fld_94f8df7cbf76416ca4253b827ae84d5c","parentId":"wrk_e0c56d5920114de58ae9b756107d37a9","modified":1656913488827,"created":1656913475030,"name":"upload","description":"","environment":{},"environmentPropertyOrder":null,"metaSortKey":-1652358423058.625,"_type":"request_group"},{"_id":"req_e287242abb8447118fa6ddaef9f6b14d","parentId":"fld_94f8df7cbf76416ca4253b827ae84d5c","modified":1656915424250,"created":1651307373323,"url":"http://localhost:3001/upload/multiple","name":"upload multi","description":"","method":"POST","body":{"mimeType":"multipart/form-data","params":[{"id":"pair_9759a57717a54994bbf14157386f33b9","name":"myphoto","value":"","description":"","type":"file","fileName":"/Users/leekh/Dropbox (아이티페이퍼)/카메라 백업/배경화면/여름/01636_smoothevening_2560x1600.jpg"},{"id":"pair_f692a26e1cc1439a966bf26e6b0aa67f","name":"myphoto","value":"","description":"","type":"file","fileName":"/Users/leekh/Dropbox (아이티페이퍼)/카메라 백업/배경화면/여름/01661_privatedocksunset_2560x1600.jpg"},{"id":"pair_a998f92c5c2046f9841cb58292877199","name":"myphoto","value":"","description":"","type":"file","fileName":"/Users/leekh/Dropbox (아이티페이퍼)/카메라 백업/배경화면/여름/01775_countrywaterfallcoudraysalbertfrance_2560x1600.jpg"}]},"parameters":[],"headers":[{"name":"Content-Type","value":"multipart/form-data","id":"pair_87dbb8040f5a4a37a1fcca2f594f3554"}],"authentication":{},"metaSortKey":-1651307373323,"isPrivate":false,"settingStoreCookies":true,"settingSendCookies":true,"settingDisableRenderRequestBody":false,"settingEncodeUrl":true,"settingRebuildPath":true,"settingFollowRedirects":"global","_type":"request"},{"_id":"req_2a11ad157cc841f19b18ab4d8ba4d541","parentId":"fld_e2d119f028f14e1ea1c9170e108090b4","modified":1656991207684,"created":1656942561129,"url":"http://localhost:3001/api_test/custom_error","name":"custom_error","description":"","method":"GET","body":{},"parameters":[],"headers":[],"authentication":{},"metaSortKey":-1656942561129,"isPrivate":false,"settingStoreCookies":true,"settingSendCookies":true,"settingDisableRenderRequestBody":false,"settingEncodeUrl":true,"settingRebuildPath":true,"settingFollowRedirects":"global","_type":"request"},{"_id":"fld_e2d119f028f14e1ea1c9170e108090b4","parentId":"wrk_e0c56d5920114de58ae9b756107d37a9","modified":1656991192084,"created":1656942553610,"name":"ApiTest","description":"","environment":{},"environmentPropertyOrder":null,"metaSortKey":-1652358423008.625,"_type":"request_group"},{"_id":"req_d96d7d81b64e473ebbc151a0671a464a","parentId":"fld_e2d119f028f14e1ea1c9170e108090b4","modified":1656991440343,"created":1656991405941,"url":"http://localhost:3001/unknown","name":"unknown(not found)","description":"","method":"GET","body":{},"parameters":[],"headers":[],"authentication":{},"metaSortKey":-1656942561104,"isPrivate":false,"settingStoreCookies":true,"settingSendCookies":true,"settingDisableRenderRequestBody":false,"settingEncodeUrl":true,"settingRebuildPath":true,"settingFollowRedirects":"global","_type":"request"},{"_id":"req_269b0144fd1c4058855749ae5d2bd3f8","parentId":"fld_e2d119f028f14e1ea1c9170e108090b4","modified":1656991615572,"created":1656942655823,"url":"http://localhost:3001/api_test/make_result","name":"make_result","description":"","method":"GET","body":{},"parameters":[{"id":"pair_53393c717ba44be599203fd8be0681cf","name":"num1","value":"200","description":""},{"id":"pair_76dfc1b6740949d8bd6ebe9416928fd8","name":"num2","value":"500","description":""}],"headers":[],"authentication":{},"metaSortKey":-1656942561079,"isPrivate":false,"settingStoreCookies":true,"settingSendCookies":true,"settingDisableRenderRequestBody":false,"settingEncodeUrl":true,"settingRebuildPath":true,"settingFollowRedirects":"global","_type":"request"},{"_id":"req_0aad435415894b3c988e4a8546dd17b0","parentId":"fld_42d24b5c5f194808aebbb0ed89ab23bd","modified":1664089153194,"created":1657178525954,"url":"http://10.211.55.8:3001/department/","name":"department","description":"","method":"GET","body":{},"parameters":[{"id":"pair_95ea23a6679248afa23e9f4569a66a95","name":"query","value":"Node","description":"","disabled":true},{"id":"pair_597c92af777c46bdaa748785dc0d2e04","name":"page","value":"1","description":"","disabled":false},{"id":"pair_ece3546f50b442c0ad40681aef777e1d","name":"rows","value":"5","description":"","disabled":false}],"headers":[],"authentication":{},"metaSortKey":-1657178525954,"isPrivate":false,"settingStoreCookies":true,"settingSendCookies":true,"settingDisableRenderRequestBody":false,"settingEncodeUrl":true,"settingRebuildPath":true,"settingFollowRedirects":"global","_type":"request"},{"_id":"fld_42d24b5c5f194808aebbb0ed89ab23bd","parentId":"wrk_e0c56d5920114de58ae9b756107d37a9","modified":1657178524496,"created":1657178521231,"name":"RestfulAPI","description":"","environment":{},"environmentPropertyOrder":null,"metaSortKey":-1652358422958.625,"_type":"request_group"},{"_id":"req_1f7fdec45772430381b28fc8526f4f3a","parentId":"fld_42d24b5c5f194808aebbb0ed89ab23bd","modified":1657260743751,"created":1657178806071,"url":"http://localhost:3001/department/205","name":"department/deptno","description":"","method":"GET","body":{},"parameters":[],"headers":[],"authentication":{},"metaSortKey":-1657178525904,"isPrivate":false,"settingStoreCookies":true,"settingSendCookies":true,"settingDisableRenderRequestBody":false,"settingEncodeUrl":true,"settingRebuildPath":true,"settingFollowRedirects":"global","_type":"request"},{"_id":"req_04e95a3280474185b3821500a40084fb","parentId":"fld_42d24b5c5f194808aebbb0ed89ab23bd","modified":1657260930968,"created":1657179188730,"url":"http://localhost:3001/department","name":"department","description":"","method":"POST","body":{"mimeType":"application/x-www-form-urlencoded","params":[{"id":"pair_cc2776ba7a384cb8915831bb827415eb","name":"dname","value":"새로운 학과","description":""},{"id":"pair_3b29e6fbbb204ae282aa97b7e9993f79","name":"loc","value":"여긴어디?","description":""}]},"parameters":[],"headers":[{"name":"Content-Type","value":"application/x-www-form-urlencoded","id":"pair_99363f738fd24d399d4f9bdff0f5c4ff"}],"authentication":{},"metaSortKey":-1657178525854,"isPrivate":false,"settingStoreCookies":true,"settingSendCookies":true,"settingDisableRenderRequestBody":false,"settingEncodeUrl":true,"settingRebuildPath":true,"settingFollowRedirects":"global","_type":"request"},{"_id":"req_9361d5d9df3c4daaad6778e25542b697","parentId":"fld_42d24b5c5f194808aebbb0ed89ab23bd","modified":1657261021963,"created":1657179302877,"url":"http://localhost:3001/department/269","name":"department","description":"","method":"PUT","body":{"mimeType":"application/x-www-form-urlencoded","params":[{"id":"pair_3b8c45f0c7cd4a05b382c01236c4a89b","name":"dname","value":"수정된학과","description":""},{"id":"pair_77535922098546e9a4de33535359c443","name":"loc","value":"나는누구?","description":""}]},"parameters":[],"headers":[{"name":"Content-Type","value":"application/x-www-form-urlencoded","id":"pair_f77fbfa7ccf94365a49609f9599277e4"}],"authentication":{},"metaSortKey":-1657178525804,"isPrivate":false,"settingStoreCookies":true,"settingSendCookies":true,"settingDisableRenderRequestBody":false,"settingEncodeUrl":true,"settingRebuildPath":true,"settingFollowRedirects":"global","_type":"request"},{"_id":"req_0a135f53f28148f1b5b3381f1d9c883b","parentId":"fld_42d24b5c5f194808aebbb0ed89ab23bd","modified":1657590791996,"created":1657179396912,"url":"http://localhost:3001/department/245","name":"department","description":"","method":"DELETE","body":{},"parameters":[],"headers":[],"authentication":{},"metaSortKey":-1657178525754,"isPrivate":false,"settingStoreCookies":true,"settingSendCookies":true,"settingDisableRenderRequestBody":false,"settingEncodeUrl":true,"settingRebuildPath":true,"settingFollowRedirects":"global","_type":"request"},{"_id":"env_b614f4f8c88fe3f355b3bce8bb2f65fbb2c9ac2b","parentId":"wrk_e0c56d5920114de58ae9b756107d37a9","modified":1656915643288,"created":1651285914880,"name":"Base Environment","data":{},"dataPropertyOrder":{},"color":null,"isPrivate":false,"metaSortKey":1651285914880,"_type":"environment"},{"_id":"jar_b614f4f8c88fe3f355b3bce8bb2f65fbb2c9ac2b","parentId":"wrk_e0c56d5920114de58ae9b756107d37a9","modified":1657273442298,"created":1651285914880,"name":"Default Jar","cookies":[{"key":"PM_CK_loc","value":"73ffed94cb408b12124ec208c16894d7ca09937d57a5d9796404fcf5c98caa81","expires":"2022-07-06T01:30:09.000Z","domain":"localhost","path":"/","httpOnly":true,"hostOnly":true,"creation":"2022-07-05T01:30:09.737Z","lastAccessed":"2022-07-05T01:30:09.737Z","id":"2886672692925296"},{"key":"my_msg","value":"j%3Anull","expires":"2022-07-06T03:03:45.000Z","maxAge":30,"domain":"localhost","path":"/","hostOnly":true,"creation":"2022-07-05T01:30:32.781Z","lastAccessed":"2022-07-06T03:03:15.176Z","id":"43144754694492304"},{"key":"my_msg_signed","value":"s%3Aj%3Anull.tycsBD0GX47L1F2GnM%2F%2BVwQHs%2B3N%2FZuLLSB3He2U3uE","expires":"2022-07-06T03:03:45.000Z","maxAge":30,"domain":"localhost","path":"/","hostOnly":true,"creation":"2022-07-05T01:30:32.781Z","lastAccessed":"2022-07-06T03:03:15.176Z","id":"6857487597015486"},{"key":"connect.sid","value":"s%3AjsurkM2geRsRlREuqp7_fsyqZID4aYO7.mRRCTvqNr9B%2FLQtpFRFmzq8PQCI%2Fq4g6Ad10Gl0T%2Fz0","domain":"localhost","path":"/","httpOnly":true,"hostOnly":true,"creation":"2022-07-05T01:30:48.508Z","lastAccessed":"2022-07-08T09:44:02.297Z","id":"007705658686951278"}],"_type":"cookie_jar"},{"_id":"spc_9f5e6baa36b746c386df7b77e84b2841","parentId":"wrk_e0c56d5920114de58ae9b756107d37a9","modified":1651285914878,"created":1651285914878,"fileName":"Node 수업","contents":"","contentType":"yaml","_type":"api_spec"}]}